mltt/__init__.py
mltt/checker.py
mltt/context.py
mltt/syntax.py
mltt/core/__init__.py
mltt/core/checker.py
mltt/core/evaluator.py
mltt/core/normalizer.py
mltt/syntax/__init__.py
mltt/syntax/terms.py
mltt/syntax/values.py
tests/__init__.py
tests/test_basic.py
tests/test_checker.py
tests/test_evaluator.py
tests/test_fuzzing.py
mltt_resolver-0.1.0.0.2.dist-info/METADATA
mltt_resolver-0.1.0.0.2.dist-info/WHEEL
mltt_resolver-0.1.0.0.2.dist-info/top_level.txt
mltt_resolver-0.1.0.0.2.dist-info/RECORD
